elan_scissors/__init__.py
elan_scissors/cli.py
elan_scissors-0.0.2.dist-info/LICENSE
elan_scissors-0.0.2.dist-info/METADATA
elan_scissors-0.0.2.dist-info/WHEEL
elan_scissors-0.0.2.dist-info/entry_points.txt
elan_scissors-0.0.2.dist-info/top_level.txt
elan_scissors-0.0.2.dist-info/RECORD
